Workbook

Sheet COMPANY_INFO
A1: COMPANY INFO — central inputs for this template
A2: Update the values in column C. All other tabs reference these.
A4: Identity | D4: Notes
A5: Company name | C5: Space Exploration Technologies Corp. (SpaceX) | D5: Used in the IPO_Analysis title
A6: Ticker | C6: SPCX
A7: Exchange | C7: NYSE
A8: Industry / sector | C8: Aerospace / Connectivity / AI
A9: Report date | C9: May 20, 2026 (preliminary S-1)
A11: Fiscal years | D11: Notes
A12: Latest fiscal year | C12: FY 2025 | D12: Drives all year headers on every tab
A13: Prior year | C13: FY 2024
A14: Year +1 (forecast) | C14: FY 2026E
A15: Year +2 (forecast) | C15: FY 2027E
A16: Year +3 (forecast) | C16: FY 2028E
A17: Year +4 (forecast) | C17: FY 2029E
A19: Offering structure | D19: Notes
A20: Underwriter / lead bookrunner | C20: Goldman Sachs / Morgan Stanley (placeholder)
A21: Use of proceeds (one-liner) | C21: GP&E, AI/data center capex, debt repayment, working capital
A22: Lock-up period (days) | C22: 180
A23: Greenshoe % of base | C23: 0.15 | D23: Used by IPO_Analysis to compute greenshoe shares
A24: Underwriter discount % | C24: 0.07 | D24: Net proceeds = gross * (1 - discount)
A26: Color legend
A27: Blue | C27: Hardcoded inputs — change these
A28: Black | C28: Formulas — do not overwrite
A29: Green | C29: Links from another tab
A30: Red | C30: External / disclaimer / negative variance

Sheet TERMS
A1: *THIS SHEET IS FOR EDUCATION AND INFORMATIONAL PURPOSES ONLY -> ASSUME THERE ARE ERRORS -> NOT AN ENDORSEMENT TO BUY OR SELL SECURITIES DO YOUR OWN WORK
A2: *BY OPENING THIS SHEET YOU AGREE THIS IS FOR INFORMATIONAL PURPOSES AND NOTHING IN HERE IS ADVICE
A3: **DRAFT SUBJECT TO CHANGE

Sheet TAM
A1: SpaceX TAM & Market Opportunity — Per S-1 (May 20, 2026)
A2: All values in $B. Source: SpaceX S-1 preliminary filing, May 20, 2026.
A4: SECTION 1: HEADLINE TAM
A5: Company estimates quantifiable TAM at $28.5T (excludes China and Russia).
A7: Segment | B7: TAM ($B) | C7: % of Quantified TAM | D7: Company Framing
A8: Space | B8: 370 | C8: =B8/$B$11 -> 0.013009845 | D8: Launch, manufacturing, PNT, satellite ops, gov agency uncontracted spend
A9: Connectivity | B9: 1610 | C9: =B9/$B$11 -> 0.056610408 | D9: Starlink Broadband + Starlink Mobile
A10: AI | B10: 26460 | C10: =B10/$B$11 -> 0.93037975 | D10: Infrastructure, subscriptions, advertising, enterprise applications
A11: Total quantified TAM (sum) | B11: =SUM(B8:B10) -> 28440 | C11: =B11/$B$11 -> 1 | D11: Rounded company estimate = $28.5T
A12: Company rounded figure | B12: 28500
A13: Rounding gap | B13: =B12-B11 -> 60
A15: SECTION 2: SEGMENT BUILD
A17: Sub-segment | B17: TAM ($B) | C17: Parent segment | D17: Methodology / Source
A18: Space-enabled solutions | B18: 370 | C18: Space | D18: Novaspace 2025 market estimate
A19: Starlink Broadband — Consumer | B19: 660 | C19: Connectivity | D19: 1.8B households × $31/mo × 12 = $670B (rounded to $660B)
A20: Starlink Broadband — Enterprise | B20: 200 | C20: Connectivity | D20: Grand View Research, global biz broadband 2025
A21: Starlink Broadband — Government | B21: 5 | C21: Connectivity | D21: Novaspace, publicly disclosed gov programs only
A22: Starlink Mobile | B22: 740 | C22: Connectivity | D22: 8.0B devices × $8/mo × 12 = $768B (stated $740B)
A23: AI Infrastructure | B23: 2400 | C23: AI | D23: 104M GPUs × 80% utilization × 8,760 hrs × $3.33/GPU-hr = $2.43T
A24: AI Consumer Subscriptions | B24: 760 | C24: AI | D24: 5.5B population age 10+ × $12/mo × 12 = $792B
A25: AI Digital Advertising | B25: 600 | C25: AI | D25: S&P Global Market Intelligence, 2025 global digital ad spend
A26: AI Enterprise Applications | B26: 22700 | C26: AI | D26: DCO 2026 digital economy estimate (broad ceiling)
A27: Total quantified sub-segments | B27: =SUM(B18:B26) -> 28435 | D27: Sum of all quantified sub-segments
A29: SECTION 3: KEY FORMULAS & ASSUMPTIONS
A31: Starlink Consumer Broadband | B31: Input | C31: Value | D31: Notes
B32: Global households (2025) | C32: 1.8 | D32: Billions
B33: Weighted avg monthly ARPU | C33: 31 | D33: $/month
B34: High-income ARPU | C34: 43 | D34: $/month
B35: Upper-middle ARPU | C35: 16 | D35: $/month
B36: Lower-middle / low-income ARPU | C36: 9 | D36: $/month
B37: Calculated TAM ($B) | C37: =C32*C33*12 -> 669.6 | D37: Households × ARPU × 12
B38: Company stated TAM ($B) | C38: 660 | D38: Rounded / region-weighted
A40: Starlink Mobile | B40: Input | C40: Value | D40: Notes
B41: Global mobile devices (Dec 31 2025) | C41: 8 | D41: Billions
B42: Weighted avg monthly ARPU | C42: 8 | D42: $/month
B43: High-income ARPU | C43: 18 | D43: $/month
B44: Upper-middle ARPU | C44: 5 | D44: $/month
B45: Lower-middle / low-income ARPU | C45: 2 | D45: $/month
B46: Calculated TAM ($B) | C46: =C41*C42*12 -> 768 | D46: Devices × ARPU × 12
B47: Company stated TAM ($B) | C47: 740 | D47: Rounded down for region weighting
A49: AI Infrastructure | B49: Input | C49: Value | D49: Notes
B50: Global data center demand 2030 (GW) | C50: 235
B51: AI workload share | C51: 0.7
B52: AI data center demand (GW) | C52: =C50*C51 -> 164.5
B53: Target PUE | C53: 1.2
B54: IT load after PUE (GW) | C54: =C52/C53 -> 137.08333
B55: GPU power (kW per GPU) | C55: 1.3
B56: Implied GPU count (M) | C56: =C54*1000/C55 -> 105448.72
B57: Company stated GPU count (M) | C57: 104
B58: Utilization rate | C58: 0.8
B59: Hours per year | C59: 8760
B60: GPU rental rate ($/GPU-hour) | C60: 3.33
B61: Calculated TAM ($B) | C61: =C57*1000000*C58*C59*C60/1000000000 -> 2427.0106 | D61: GPUs × utilization × hrs × rate ÷ $1B
B62: Company stated TAM ($B) | C62: 2400
A64: AI Consumer Subscriptions | B64: Input | C64: Value
B65: Global population age 10+ (B) | C65: 5.5
B66: Weighted avg monthly ARPU | C66: 12
B67: Calculated TAM ($B) | C67: =C65*C66*12 -> 792
B68: Company stated TAM ($B) | C68: 760
A70: SECTION 4: FUTURE / UNQUANTIFIED MARKETS
A71: Not in $28.5T quantified TAM — narrative upside only.
A73: Future market | B73: Quantified? | C73: Company framing
A74: Lunar economy (transport, infra, comms, energy, mfg, mining) | B74: No | C74: Too uncertain on timing, adoption, regulatory
A75: Long-haul point-to-point terrestrial travel | B75: No | C75: Starship-enabled
A76: Space tourism | B76: No | C76: Emerging market
A77: In-orbit manufacturing | B77: No | C77: Enabled by lower launch costs + orbital infra
A78: Asteroid mining | B78: No | C78: Not currently commercial
A79: Passenger/cargo transport to Moon | B79: No | C79: Emerging market
A80: Passenger/cargo transport to Mars | B80: No | C80: Does not exist today at commercial scale
A81: Energy production on Moon and Mars | B81: No | C81: Tied to lunar/Mars industrialization
A82: Manufacturing on Moon and Mars | B82: No | C82: Potentially includes satellites and advanced chips
A83: Human augmentation | B83: No | C83: Emerging future opportunity
A85: SECTION 5: KEY CRITIQUES
A87: Issue | B87: Why it matters
A88: TAM ≠ revenue guidance | B88: Company explicitly cautions estimates are imprecise / based on assumptions.
A89: AI dominates 93% of TAM | B89: A 'SpaceX = rockets + Starlink' frame misses the IPO narrative.
A90: Enterprise AI bucket ($22.7T) uses entire digital economy | B90: Much broader than conventional enterprise software TAM. Treat as ceiling, not SOM.
A91: Starlink Broadband math is auditable | B91: Households × ARPU. Stated $660B vs simple math $670B — minor rounding.
A92: Starlink Mobile math is auditable | B92: Devices × ARPU. Stated $740B vs simple math $768B — region-weighted.
A93: Space TAM understates strategic value | B93: Only $370B in TAM, but framed as unlock for Connectivity, AI, lunar, Mars.
A94: Future markets are pure narrative upside | B94: Lunar, Mars, asteroid mining, point-to-point all excluded from $28.5T.
A96: SECTION 6: MODEL INPUT TABLE
A97: Clean reference for downstream modeling tabs (Starlink Broadband, AI Compute, etc.).
A99: Segment | B99: Market | C99: TAM ($B) | D99: Model bucket | E99: Formula Confidence
A100: Space | B100: Space-enabled solutions | C100: 370 | D100: Space | E100: Medium
A101: Connectivity | B101: Consumer broadband | C101: 660 | D101: Starlink Broadband | E101: High
A102: Connectivity | B102: Enterprise broadband | C102: 200 | D102: Starlink Enterprise | E102: Medium
A103: Connectivity | B103: Government communications | C103: 5 | D103: Starshield / gov connectivity | E103: Medium
A104: Connectivity | B104: Starlink Mobile | C104: 740 | D104: Starlink Mobile | E104: High
A105: AI | B105: AI infrastructure | C105: 2400 | D105: Compute services / infrastructure | E105: Medium
A106: AI | B106: Consumer subscriptions | C106: 760 | D106: Grok / X subscriptions | E106: Medium
A107: AI | B107: Digital advertising | C107: 600 | D107: X ads | E107: Medium
A108: AI | B108: Enterprise applications | C108: 22700 | D108: Grok Enterprise / Macrohard / agentic AI | E108: Low-Medium
A109: Future | B109: Lunar / Mars / in-orbit / etc. | D109: Optional long-dated call options | E109: Low (narrative only)
A110: Total Quantified | C110: =SUM(C100:C108) -> 28435

Sheet IPO_Analysis
A1: =COMPANY_INFO!C5 & " — IPO Analysis" -> Space Exploration Technologies Corp. (SpaceX) — IPO Analysis
A2: *THIS SHEET IS FOR EDUCATION AND INFORMATIONAL PURPOSES ONLY -> ASSUME THERE ARE ERRORS -> NOT AN ENDORSEMENT TO BUY OR SELL SECURITIES DO YOUR OWN WORK
A3: SECTION 1: IPO OFFERING DETAILS & VALUATION
A4: ($ in thousands, except per share and share data)
C5: Assumptions | E5: Implied Valuation
A6: Offering Details
A7: Primary shares offered | C7: 800000000
A8: Greenshoe (15% over-allotment) | C8: =C7*0.15 -> 120000000
A9: Total shares offered (incl. greenshoe) | C9: =C7+C8 -> 920000000
A11: Price Range
A12: Low | C12: 110
A13: Midpoint | C13: =(C12+C14)/2 -> 125
A14: High | C14: 140
C15: =+C13*C9/1000000 -> 115000
A16: Gross Proceeds (at midpoint)
A17: Primary offering | E17: =C7*C13 -> 100000000000
A18: Incl. greenshoe | E18: =C9*C13 -> 115000000000
A20: Share Count Summary | C20: Shares
A21: Pre-IPO shares (Class A + B + N) | C21: =Share_Count!C24 -> 12520310769
A22: (+) Primary IPO shares | C22: =C7 -> 800000000
A23: (+) Greenshoe shares | C23: =C8 -> 120000000
A24: Basic shares post-IPO (excl. greenshoe) | C24: =C21+C22 -> 13320310769
A25: Basic shares post-IPO (incl. greenshoe) | C25: =C21+C22+C23 -> 13440310769
A27: (+) Stock options outstanding | C27: =Share_Count!D9 -> 934000000
A28: (+) RSUs outstanding | C28: =Share_Count!D10 -> 129000000
A29: (+) Performance & market condition awards | C29: =Share_Count!D12 -> 0
A30: (+) EchoStar spectrum shares | C30: =Share_Count!D13 -> 261800000
A31: (+) Cursor acquisition option shares | C31: =Share_Count!D14 -> 0
A32: Fully diluted shares post-IPO | C32: =C25+C27+C28+C29+C30+C31 -> 14765110769
A34: Implied Valuation (at midpoint price) | E34: Basic | F34: Fully Diluted
A35: Implied market capitalization | E35: =C25*C13 -> 1680038846125 | F35: =C32*C13 -> 1845638846125
A37: (−) Cash & equivalents | E37: =-Annual_Financials!D34*1000 -> -24747000000
A38: (−) Marketable securities | E38: =-Annual_Financials!D35*1000 -> 0
A39: (−) Digital assets | E39: =-Annual_Financials!D36*1000 -> -1637000000
A40: (−) Net IPO proceeds (cash added by IPO) | E40: =-E17*(1-COMPANY_INFO!C24) -> -93000000000
A41: (+) Total debt (current + LT) | E41: =(Annual_Financials!D50+Annual_Financials!D54)*1000 -> 22896000000
A42: Net cash bridge (EV adjustment) | E42: =E37+E38+E39+E40+E41 -> -96488000000
A43: Implied enterprise value (EV) | E43: =E35+E42 -> 1583550846125 | F43: =F35+E42 -> 1749150846125
A45: Valuation Multiples (at midpoint, FY 2025 basis) | E45: Basic | F45: Fully Diluted
A46: FY 2025 Revenue ($000) | C46: =Annual_Financials!D6 -> 18674000
A47: FY 2025 Operating Income ($000) | C47: =Annual_Financials!D15 -> -2589000
A48: FY 2025 EBITDA ($000) | C48: =Annual_Financials!D15+Annual_Financials!D67+Annual_Financials!D13+Annual_Financials!D14 -> 5277000
A49: FY 2025 Adj. EBITDA ($000) | C49: =Annual_Financials!D27 -> 6584000
A51: EV / FY 2025 Revenue | E51: =E43/(C46*1000) -> 84.799767 | F51: =F43/(C46*1000) -> 93.667712
A52: EV / FY 2025 Operating Income | E52: =IF(C47>0,E43/(C47*1000),"N/M") -> N/M | F52: =IF(C47>0,F43/(C47*1000),"N/M") -> N/M
A53: EV / FY 2025 EBITDA | E53: =IF(C48>0,E43/(C48*1000),"N/M") -> 300.08544 | F53: =IF(C48>0,F43/(C48*1000),"N/M") -> 331.4669
A54: EV / FY 2025 Adj. EBITDA | E54: =IF(C49>0,E43/(C49*1000),"N/M") -> 240.51501 | F54: =IF(C49>0,F43/(C49*1000),"N/M") -> 265.6669
A55: Price / FY 2025 Revenue (mkt cap basis) | E55: =E35/(C46*1000) -> 89.966737 | F55: =F35/(C46*1000) -> 98.834682
A58: SECTION 2: HISTORICAL INCOME STATEMENT (GAAP)
A59: ($ in thousands)
C61: =COMPANY_INFO!C13 -> FY 2024 | D61: =COMPANY_INFO!C12 -> FY 2025 | E61: =COMPANY_INFO!C14 -> FY 2026E | F61: =COMPANY_INFO!C15 -> FY 2027E | G61: =COMPANY_INFO!C16 -> FY 2028E | H61: =COMPANY_INFO!C17 -> FY 2029E
C62: ← Historical Actuals → | E62: ← Forecast / Estimates →
A63: Revenue Build
A64: Space (customer launches + Launch & Development) | C64: 3796000 | D64: 4086000 | E64: =D64*(1+E66) -> 4494600 | F64: =E64*(1+F66) -> 5168790 | G64: =F64*(1+G66) -> 6099172.2 | H64: =G64*(1+H66) -> 7319006.6
A65: % of total revenue | C65: =C64/C75 -> 0.27085266 | D65: =D64/D75 -> 0.2188069 | E65: =E64/E75 -> 0.12692935 | F65: =F64/F75 -> 0.10829119 | G65: =G64/G75 -> 0.096240967 | H65: =H64/H75 -> 0.091175615
A66: YoY growth | C66: 0.0672 | D66: =D64/C64-1 -> 0.076396207 | E66: 0.1 | F66: 0.15 | G66: 0.18 | H66: 0.2 | I66: *PLACEHOLDERS MAKE YOUR OWN FORECASTS
A68: Connectivity (Starlink Broadband + Mobile + Enterprise/Gov) | C68: 7599000 | D68: 11387000 | E68: =D68*(1+E70) -> 16511150 | F68: =E68*(1+F70) -> 23115610 | G68: =F68*(1+G70) -> 30050293 | H68: =G68*(1+H70) -> 37562866
A69: % of total revenue | C69: =C68/C75 -> 0.54220478 | D69: =D68/D75 -> 0.6097783 | E69: =E68/E75 -> 0.46628166 | F69: =F68/F75 -> 0.48429457 | G69: =G68/G75 -> 0.47417406 | H69: =H68/H75 -> 0.46793473
A70: YoY growth | C70: 0.9641 | D70: =D68/C68-1 -> 0.49848664 | E70: 0.45 | F70: 0.4 | G70: 0.3 | H70: 0.25 | I70: *PLACEHOLDERS MAKE YOUR OWN FORECASTS
A72: AI (X/Grok subs, Advertising, AI Solutions, Compute) | C72: 2620000 | D72: 3201000 | E72: =D72*(1+E74) -> 14404500 | F72: =E72*(1+F74) -> 19446075 | G72: =F72*(1+G74) -> 27224505 | H72: =G72*(1+H74) -> 35391856 | I72: *ANTHROPIC $1.25B/month × ~7 months full-rate (Jul–Dec 2026) + 2 months ramp (May–Jun, assume 50% rate) ≈ $9.5B incremental AI revenue from Anthropic alone
A73: % of total revenue | C73: =C72/C75 -> 0.18694256 | D73: =D72/D75 -> 0.1714148 | E73: =E72/E75 -> 0.40678899 | F73: =F72/F75 -> 0.40741424 | G73: =G72/G75 -> 0.42958497 | H73: =H72/H75 -> 0.44088965
A74: YoY growth | C74: -0.1152 | D74: =D72/C72-1 -> 0.22175573 | E74: 3.5 | F74: 0.35 | G74: 0.4 | H74: 0.3
A75: Total Revenue | C75: =C64+C68+C72 -> 14015000 | D75: =D64+D68+D72 -> 18674000 | E75: =E64+E68+E72 -> 35410250 | F75: =F64+F68+F72 -> 47730475 | G75: =G64+G68+G72 -> 63373970 | H75: =H64+H68+H72 -> 80273729
A76: YoY growth | C76: =C75/Annual_Financials!F6-1 -> 0.34928276 | D76: =D75/C75-1 -> 0.33242954 | E76: =E75/D75-1 -> 0.89623273 | F76: =F75/E75-1 -> 0.34792821 | G76: =G75/F75-1 -> 0.32774648 | H76: =(H75/C75)^(1/5)-1 -> 0.41773829 | I76: IMPLIED 5 YR CAGR
A77: Cumulative FY26E–FY29E revenue | H77: =E75+F75+G75+H75 -> 2.2678842e+08
A78: Segment Adjusted EBITDA Build
A79: Space — Adj EBITDA | C79: 1154000 | D79: 653000 | E79: =E64*E80 -> 898920 | F79: =F64*F80 -> 1292197.5 | G79: =G64*G80 -> 1829751.7 | H79: =H64*H80 -> 2195702
A80: Adj EBITDA margin | C80: =C79/C64 -> 0.30400421 | D80: =D79/D64 -> 0.159814 | E80: 0.2 | F80: 0.25 | G80: 0.3 | H80: 0.3
A82: Connectivity — Adj EBITDA | C82: 3849000 | D82: 7168000 | E82: =E68*E83 -> 10732248 | F82: =F68*F83 -> 15025146 | G82: =G68*G83 -> 19532690 | H82: =H68*H83 -> 24415863
A83: Adj EBITDA margin | C83: =C82/C68 -> 0.50651402 | D83: =D82/D68 -> 0.62948977 | E83: 0.65 | F83: 0.65 | G83: 0.65 | H83: 0.65
A85: AI — Adj EBITDA | C85: 347000 | D85: -1237000 | E85: =E72*E86 -> 2880900 | F85: =F72*F86 -> 5833822.5 | G85: =G72*G86 -> 9528576.8 | H85: =H72*H86 -> 8847964.1
A86: Adj EBITDA margin | C86: =C85/C72 -> 0.13244275 | D86: =D85/D72 -> -0.38644174 | E86: 0.2 | F86: 0.3 | G86: 0.35 | H86: 0.25
A88: Total Adjusted EBITDA (non-GAAP) | C88: =C79+C82+C85 -> 5350000 | D88: =D79+D82+D85 -> 6584000 | E88: =E79+E82+E85 -> 14512068 | F88: =F79+F82+F85 -> 22151166 | G88: =G79+G82+G85 -> 30891019 | H88: =H79+H82+H85 -> 35459529
A89: Adj EBITDA margin | C89: =C88/C75 -> 0.38173386 | D89: =D88/D75 -> 0.35257577 | E89: =E88/E75 -> 0.40982675 | F89: =F88/F75 -> 0.46408854 | G89: =G88/G75 -> 0.48744017 | H89: =H88/H75 -> 0.44173267 | I89: *WHAT ARE LT EBITDA MARGINS HERE?
A90: YoY growth | C90: =C88/Annual_Financials!F27-1 -> 0.40015703 | D90: =D88/C88-1 -> 0.23065421 | E90: =E88/D88-1 -> 1.2041415 | F90: =F88/E88-1 -> 0.52639632 | G90: =G88/F88-1 -> 0.39455495 | H90: =H88/G88-1 -> 0.14789122
A92: Bridge: Adj EBITDA → Net Income
A94: (−) Stock-based compensation | C94: 981000 | D94: 1307000 | E94: =E95*E75 -> 3541025 | F94: =F95*F75 -> 3341133.3 | G94: =G95*G75 -> 4436177.9 | H94: =H95*H75 -> 5619161.1 | I94: *PLACEHOLDERS MAKE YOUR OWN FORECASTS from D&A Build
A95: SBC % of revenue | C95: =C94/C75 -> 0.069996432 | D95: =D94/D75 -> 0.069990361 | E95: 0.1 | F95: 0.07 | G95: 0.07 | H95: 0.07
A97: EBITDA (non-GAAP) | C97: =C88-C94-Annual_Financials!E13-Annual_Financials!E14 -> 4093000 | D97: =D88-D94-Annual_Financials!D13-Annual_Financials!D14 -> 4752000 | E97: =E88-E94 -> 10971042 | F97: =F88-F94 -> 18810033 | G97: =G88-G94 -> 26454841 | H97: =H88-H94 -> 29840368 | I97: *PLACEHOLDERS MAKE YOUR OWN FORECASTS
A98: EBITDA margin | C98: =C97/C75 -> 0.29204424 | D98: =D97/D75 -> 0.25447146 | E98: =E97/E75 -> 0.30982675 | F98: =F97/F75 -> 0.39408854 | G98: =G97/G75 -> 0.41744017 | H98: =H97/H75 -> 0.37173267
A100: (−) Depreciation & amortization | C100: 3627000 | D100: 7341000 | E100: =E101*E75 -> 12039485 | F100: =F101*F75 -> 14319142 | G100: =G101*G75 -> 16477232 | H100: =H101*H75 -> 19265695 | I100: *YOU WILL DEF NEED TO BUILD A D&A SCHEDULE
A101: D&A % of revenue | C101: =C100/C75 -> 0.25879415 | D101: =D100/D75 -> 0.39311342 | E101: 0.34 | F101: 0.3 | G101: 0.26 | H101: 0.24
A103: Operating Income (Loss) [GAAP] | C103: =C97-C100 -> 466000 | D103: =D97-D100 -> -2589000 | E103: =E97-E100 -> -1068442.5 | F103: =F97-F100 -> 4490890.8 | G103: =G97-G100 -> 9977608.7 | H103: =H97-H100 -> 10574673
A104: Operating margin | C104: =C103/C75 -> 0.033250089 | D104: =D103/D75 -> -0.13864196 | E104: =E103/E75 -> -0.030173255 | F104: =F103/F75 -> 0.094088541 | G104: =G103/G75 -> 0.15744017 | H104: =H103/H75 -> 0.13173267
A106: (+/−) Net interest, taxes & other | C106: =Annual_Financials!E21-C103 -> 325000 | D106: =Annual_Financials!D21-D103 -> -2348000 | E106: -2200000 | F106: -2000000 | G106: -5500000 | H106: -5500000
A108: Net Income (Loss) [GAAP] | C108: =C103+C106 -> 791000 | D108: =D103+D106 -> -4937000 | E108: =E103+E106 -> -3268442.5 | F108: =F103+F106 -> 2490890.8 | G108: =G103+G106 -> 4477608.7 | H108: =H103+H106 -> 5074673.1
A109: Net margin | C109: =C108/C75 -> 0.056439529 | D109: =D108/D75 -> -0.26437828 | E109: =E108/E75 -> -0.092302158 | F109: =F108/F75 -> 0.05218659 | G109: =G108/G75 -> 0.070653751 | H109: =H108/H75 -> 0.063217109
A112: SECTION 3: CASH FLOW SUMMARY
A113: ($ in thousands)
C114: FY 2024 | D114: FY 2025 | E114: =COMPANY_INFO!C14 -> FY 2026E | F114: =COMPANY_INFO!C15 -> FY 2027E | G114: =COMPANY_INFO!C16 -> FY 2028E | H114: =COMPANY_INFO!C17 -> FY 2029E
A116: Operating Cash Flow (OCF) | C116: =Annual_Financials!E60 -> 5776000 | D116: =Annual_Financials!D60 -> 6785000 | E116: =E97+E125+E106+E127 -> 10541555 | F116: =F97+F125+F106+F127 -> 18241948 | G116: =G97+G125+G106+G127 -> 23489800 | H116: =H97+H125+H106+H127 -> 28354055
A117: % of total revenue | C117: =+C116/C75 -> 0.41212986 | D117: =+D116/D75 -> 0.3633394 | E117: =+E116/E75 -> 0.29769784 | F117: =+F116/F75 -> 0.38218659 | G117: =+G116/G75 -> 0.37065375 | H117: =+H116/H75 -> 0.35321711 | I117: *PLACEHOLDERS MAKE YOUR OWN FORECASTS
A118: Capital expenditures | C118: =Annual_Financials!E80 -> -11163000 | D118: =Annual_Financials!D80 -> -20737000 | E118: =E119*E75 -> -38951275 | F118: =F119*F75 -> -40570904 | G118: =G119*G75 -> -34855684 | H118: =H119*H75 -> -32109492
A119: % of total revenue | C119: =+C118/C75 -> -0.79650375 | D119: =+D118/D75 -> -1.1104745 | E119: -1.1 | F119: -0.85 | G119: -0.55 | H119: -0.4 | I119: *PLACEHOLDERS MAKE YOUR OWN FORECASTS for CAPEX SPEND TO GET TO MARS
A120: Free Cash Flow (FCF) | C120: =C116+C118 -> -5387000 | D120: =D116+D118 -> -13952000 | E120: =E116+E118 -> -28409720 | F120: =F116+F118 -> -22328956 | G120: =G116+G118 -> -11365884 | H120: =H116+H118 -> -3755437.2
A121: FCF margin | C121: =C120/C75 -> -0.38437389 | D121: =D120/D75 -> -0.74713505 | E121: =E120/E75 -> -0.80230216 | F121: =F120/F75 -> -0.46781341 | G121: =G120/G75 -> -0.17934625 | H121: =H120/H75 -> -0.046782891
A123: Key CF Addbacks / Adjustments
A124: Depreciation & amortization | C124: =Annual_Financials!E67 -> 3627000 | D124: =Annual_Financials!D67 -> 7341000 | E124: =E100 -> 12039485 | F124: =F100 -> 14319142 | G124: =G100 -> 16477232 | H124: =H100 -> 19265695
A125: Stock-based compensation | C125: =Annual_Financials!E68 -> 981000 | D125: =Annual_Financials!D68 -> 1307000 | E125: =E94 -> 3541025 | F125: =F94 -> 3341133.3 | G125: =G94 -> 4436177.9 | H125: =H94 -> 5619161.1
A126: FV change / extinguishment of fwd contract | C126: =Annual_Financials!E71 -> 0 | D126: =Annual_Financials!D71 -> 0 | E126: 0 | F126: 0 | G126: 0 | H126: 0
...

Sheet Share_Count
A1: SpaceX Fully Diluted Share Count Extract — Mar 31, 2026 pro forma
A3: Category | B3: Component | C3: Class | D3: Known Shares | E3: Include in User-Specified Total? | F3: Include in Full Diluted Total? | G3: Status | H3: Source / Notes
A4: Existing / Old Shares | B4: Pro forma Class A common (incl. preferred conversion & Class C reclass) | C4: Class A | D4: 6824581339 | E4: Y | F4: Y | G4: disclosed | H4: SpaceX S-1, §14
A5: Existing / Old Shares | B5: Pro forma Class B common | C5: Class B | D5: 5695729430 | E5: Y | F5: Y | G5: disclosed | H5: SpaceX S-1, §14
A6: Existing / Old Shares | B6: Post-3/31 share issuances (placeholder) | C6: Class A | D6: 0 | E6: Y | F6: Y | G6: blank | H6: Model input
A7: IPO Shares | B7: Common stock offered by company in IPO | C7: Class A | E7: Y | F7: Y | G7: disclosed at pricing | H7: Pricing prospectus — input in IPO_Analysis
A8: IPO Shares | B8: Underwriters' over-allotment option (greenshoe) | C8: Class A | E8: Y | F8: Y | G8: disclosed at pricing | H8: Computed in IPO_Analysis
A9: Equity Awards | B9: Outstanding stock options at Mar 31, 2026 | C9: Class A/B/C | D9: 934000000 | E9: Y | F9: Y | G9: disclosed | H9: SpaceX S-1, §15 reserve table
A10: Equity Awards | B10: Outstanding RSUs at Mar 31, 2026 | C10: Class A/B/C | D10: 129000000 | E10: Y | F10: Y | G10: disclosed | H10: SpaceX S-1, §15 reserve table
A11: Equity Awards | B11: Performance & market condition awards (excl. from diluted EPS) | C11: Class B | D11: 1319100000 | E11: Y | F11: Y | G11: disclosed | H11: SpaceX S-1, §15 + §16
A12: Equity Awards | B12: Founder / additional PRSUs (already in performance awards) | C12: Class B | D12: 0 | E12: Y | F12: Y | G12: included in row 11 | H12: SpaceX S-1, §15
A13: Warrants | B13: EchoStar spectrum equity consideration | C13: Class A | D13: 261800000 | E13: N | F13: Y | G13: disclosed | H13: SpaceX S-1, §13 + §15
A14: Warrants | B14: Cursor acquisition option ($60B / VWAP) | C14: Class A | D14: 0 | E14: N | F14: N | G14: contingent | H14: SpaceX S-1, §16
A15: Warrants | E15: N | F15: N
A16: Warrants | E16: N | F16: N
A17: Future Issuance Reserve | B17: A&R 2024 Plan future grant reserve | C17: Class A/C | D17: 500000000 | E17: Y | F17: Y | G17: disclosed | H17: SpaceX S-1, §15
A18: Future Issuance Reserve | B18: A&R 2017 ESPP reserve | C18: Class A | D18: 75000000 | E18: Y | F18: Y | G18: disclosed | H18: SpaceX S-1, §15
A19: Future Issuance Reserve | B19: Prior plan recycling / forfeitures | C19: Class A | D19: 0 | E19: Y | F19: Y | G19: future recycling
A20: Future Issuance Reserve | D20: 0 | E20: N | F20: N
A23: Summary | B23: Formula / Definition | C23: Known Shares | D23: Notes
A24: Known old shares | B24: Actual common + preferred conversion + post-12/31 Class N issued | C24: =SUM(D4:D6) -> 12520310769 | D24: Excludes unknown RSU net settlement and IPO shares
A25: Known user-specified diluted subtotal | B25: Rows marked Y in Include in User-Specified Total | C25: =SUMIF(E4:E20,"Y",D4:D20) -> 15477410769 | D25: Excludes blanks because preliminary filing omits some counts
A26: Known fully diluted subtotal incl. warrants | B26: Rows marked Y in Include in Full Diluted Total | C26: =SUMIF(F4:F20,"Y",D4:D20) -> 15739210769 | D26: Set F-column to Y for warrants that should be additive to fully diluted; flag exercised warrants N to avoid double-count
A27: Required unknown share-count fields | B27: Count of required included rows with missing Known Shares | C27: =COUNTIFS(G4:G20,"blank",F4:F20,"Y")+COUNTIFS(G4:G20,"future recycling",F4:F20,"Y") -> 2 | D27: These must be populated after final pricing / later filing amendment

Sheet Annual_Financials
A1: Annual Financials — SpaceX (FY 2025 / FY 2024 / FY 2023)
A3: Section | B3: Metric | C3: Units | D3: FY 2025 | E3: FY 2024 | F3: FY 2023 | G3: YoY % (25/24) | H3: Source / Notes
A4: Income Statement | B4: Revenue — Products (hardware) | C4: $000 | D4: 1510000 | E4: 1470000 | F4: 1093000 | G4: =IFERROR(D4/E4-1,"n.m.") -> 0.027210884 | H4: Prospectus Summary / Summary Consolidated Financial Data.
A5: Income Statement | B5: Revenue — Services (Connectivity services, Launch, Ads, AI) | C5: $000 | D5: =D6-D4 -> 17164000 | E5: =E6-E4 -> 12545000 | F5: =F6-F4 -> 9294000 | G5: =IFERROR(D5/E5-1,"n.m.") -> 0.3681945 | H5: Prospectus Summary / Summary Consolidated Financial Data.
A6: Income Statement | B6: Total revenue | C6: $000 | D6: 18674000 | E6: 14015000 | F6: 10387000 | G6: =IFERROR(D6/E6-1,"n.m.") -> 0.33242954 | H6: Prospectus Summary / Summary Consolidated Financial Data.
A7: Income Statement | B7: Cost of revenue — Products | C7: $000 | F7: =D7-E7 -> 0 | G7: n.m. | H7: Prospectus Summary / Summary Consolidated Financial Data.
A8: Income Statement | B8: Cost of revenue — Services | C8: $000 | F8: =D8-E8 -> 0 | G8: n.m. | H8: Prospectus Summary / Summary Consolidated Financial Data.
A9: Income Statement | B9: Total cost of revenue | C9: $000 | D9: 9451000 | E9: 7996000 | F9: 6110000 | G9: =IFERROR(D9/E9-1,"n.m.") -> 0.18196598 | H9: Prospectus Summary / Summary Consolidated Financial Data.
A10: Income Statement | B10: Gross profit | C10: $000 | D10: =D6-D9 -> 9223000 | E10: =E6-E9 -> 6019000 | F10: =F6-F9 -> 4277000 | G10: =IFERROR(D10/E10-1,"n.m.") -> 0.53231434 | H10: Prospectus Summary / Summary Consolidated Financial Data.
A11: Income Statement | B11: Research and development | C11: $000 | D11: 8643000 | E11: 3464000 | F11: 2105000 | G11: =IFERROR(D11/E11-1,"n.m.") -> 1.4950924 | H11: Prospectus Summary / Summary Consolidated Financial Data.
A12: Income Statement | B12: Selling, general & administrative | C12: $000 | D12: 2644000 | E12: 1813000 | F12: 1665000 | G12: =IFERROR(D12/E12-1,"n.m.") -> 0.45835632 | H12: Prospectus Summary / Summary Consolidated Financial Data.
A13: Income Statement | B13: Restructuring charges | C13: $000 | D13: 487000 | E13: 213000 | F13: 237000 | G13: =IFERROR(D13/E13-1,"n.m.") -> 1.286385 | H13: Prospectus Summary / Summary Consolidated Financial Data.
A14: Income Statement | B14: Impairment | C14: $000 | D14: 38000 | E14: 63000 | F14: 3775000 | G14: =IFERROR(D14/E14-1,"n.m.") -> -0.3968254 | H14: Prospectus Summary / Summary Consolidated Financial Data.
A15: Income Statement | B15: Loss from operations | C15: $000 | D15: =D10-D11-D12-D13-D14 -> -2589000 | E15: =E10-E11-E12-E13-E14 -> 466000 | F15: =F10-F11-F12-F13-F14 -> -3505000 | G15: =IFERROR(D15/E15-1,"n.m.") -> -6.555794 | H15: Prospectus Summary / Summary Consolidated Financial Data.
A16: Income Statement | B16: Interest expense | C16: $000 | D16: -1945000 | E16: -1580000 | F16: -1693000 | G16: =IFERROR(D16/E16-1,"n.m.") -> 0.23101266 | H16: Prospectus Summary / Summary Consolidated Financial Data.
A17: Income Statement | B17: Interest income | C17: $000 | D17: 492000 | E17: 371000 | F17: 249000 | G17: =IFERROR(D17/E17-1,"n.m.") -> 0.32614555 | H17: Prospectus Summary / Summary Consolidated Financial Data.
A18: Income Statement | B18: Other income (expense), net | C18: $000 | D18: -177000 | E18: 985000 | F18: -42000 | G18: =IFERROR(D18/E18-1,"n.m.") -> -1.1796954 | H18: Prospectus Summary / Summary Consolidated Financial Data.
A19: Income Statement | B19: Loss before income taxes | C19: $000 | D19: =D15+D16+D17+D18 -> -4219000 | E19: =E15+E16+E17+E18 -> 242000 | F19: =F15+F16+F17+F18 -> -4991000 | G19: =IFERROR(D19/E19-1,"n.m.") -> -18.433884 | H19: Prospectus Summary / Summary Consolidated Financial Data.
A20: Income Statement | B20: Provision for income taxes | C20: $000 | D20: 718000 | E20: -549000 | F20: -363000 | G20: =IFERROR(D20/E20-1,"n.m.") -> -2.3078324 | H20: Prospectus Summary / Summary Consolidated Financial Data.
A21: Income Statement | B21: Net loss | C21: $000 | D21: =D19-D20 -> -4937000 | E21: =E19-E20 -> 791000 | F21: =F19-F20 -> -4628000 | G21: =IFERROR(D21/E21-1,"n.m.") -> -7.2414665 | H21: Prospectus Summary / Summary Consolidated Financial Data.
A22: Income Statement | B22: Net loss attributable to common shareholders | C22: $000 | D22: =D21 -> -4937000 | E22: =E21 -> 791000 | F22: =F21 -> -4628000 | G22: =IFERROR(D22/E22-1,"n.m.") -> -7.2414665 | H22: Prospectus Summary / Summary Consolidated Financial Data.
A23: Per Share | B23: Basic net loss per share | C23: $/share | D23: -1.69 | E23: 0.01 | F23: -1.68 | G23: =IFERROR(D23/E23-1,"n.m.") -> -170 | H23: Prospectus Summary / Summary Consolidated Financial Data.
A24: Per Share | B24: Diluted net loss per share | C24: $/share | D24: -1.69 | E24: 0 | F24: -1.68 | G24: =IFERROR(D24/E24-1,"n.m.") -> n.m. | H24: Prospectus Summary / Summary Consolidated Financial Data.
A25: Per Share | B25: Weighted average shares — Basic (000s) | C25: 000 shares | D25: 2926000 | E25: 2848000 | F25: 2759000 | G25: =IFERROR(D25/E25-1,"n.m.") -> 0.02738764 | H25: Prospectus Summary / Summary Consolidated Financial Data.
A26: Per Share | B26: Weighted average shares — Diluted (000s) | C26: 000 shares | D26: 2926000 | E26: 9956000 | F26: 2759000 | G26: =IFERROR(D26/E26-1,"n.m.") -> -0.70610687 | H26: Prospectus Summary / Summary Consolidated Financial Data.
A27: Non-GAAP | B27: Adjusted EBITDA | C27: $000 | D27: 6584000 | E27: 5350000 | F27: 3821000 | G27: =IFERROR(D27/E27-1,"n.m.") -> 0.23065421 | H27: Prospectus Summary / Summary Consolidated Financial Data. Operating loss excluding stock-based compensation
A28: Non-GAAP | B28: Non-GAAP net loss (memo) | C28: $000 | F28: =D28-E28 -> 0 | G28: n.m. | H28: Prospectus Summary / Summary Consolidated Financial Data. Net income/loss excluding stock-based compensation and FV change/extinguishment of forward contract liability
A29: Stock-Based Compensation | B29: SBC — Cost of revenue | C29: $000 | F29: =D29-E29 -> 0 | G29: n.m. | H29: Prospectus Summary / Summary Consolidated Financial Data.
A30: Stock-Based Compensation | B30: SBC — Research and development | C30: $000 | F30: =D30-E30 -> 0 | G30: n.m. | H30: Prospectus Summary / Summary Consolidated Financial Data.
A31: Stock-Based Compensation | B31: SBC — Selling, general & administrative | C31: $000 | F31: =D31-E31 -> 0 | G31: n.m. | H31: Prospectus Summary / Summary Consolidated Financial Data.
A32: Stock-Based Compensation | B32: SBC — Restructuring/Other | C32: $000 | F32: =D32-E32 -> 0 | G32: n.m. | H32: Prospectus Summary / Summary Consolidated Financial Data.
A33: Stock-Based Compensation | B33: Total stock-based compensation expense | C33: $000 | D33: 1307000 | E33: 981000 | F33: 727000 | G33: =IFERROR(D33/E33-1,"n.m.") -> 0.33231397 | H33: Prospectus Summary / Summary Consolidated Financial Data.
A34: Balance Sheet (period-end) | B34: Cash and cash equivalents | C34: $000 | D34: 24747000 | E34: 11385000 | F34: =D34-E34 -> 13362000 | G34: =IFERROR(D34/E34-1,"n.m.") -> 1.1736495 | H34: Consolidated Balance Sheets.
A35: Balance Sheet | B35: Marketable securities (short-term) | C35: $000 | D35: 0 | E35: 800000 | F35: =D35-E35 -> -800000 | G35: n.m. | H35: Consolidated Balance Sheets.
A36: Balance Sheet | B36: Digital assets | C36: $000 | D36: 1637000 | E36: 1749000 | F36: =D36-E36 -> -112000 | G36: =IFERROR(D36/E36-1,"n.m.") -> -0.064036592 | H36: Consolidated Balance Sheets.
A37: Balance Sheet | B37: Accounts receivable, net | C37: $000 | D37: 1579000 | E37: 1052000 | F37: =D37-E37 -> 527000 | G37: =IFERROR(D37/E37-1,"n.m.") -> 0.50095057 | H37: Consolidated Balance Sheets.
A38: Balance Sheet | B38: Inventory | C38: $000 | D38: 2416000 | E38: 2003000 | F38: =D38-E38 -> 413000 | G38: =IFERROR(D38/E38-1,"n.m.") -> 0.20619071 | H38: Consolidated Balance Sheets.
A39: Balance Sheet | B39: Prepaid and other current assets | C39: $000 | D39: 2210000 | E39: 868000 | F39: =D39-E39 -> 1342000 | G39: =IFERROR(D39/E39-1,"n.m.") -> 1.5460829 | H39: Consolidated Balance Sheets.
A40: Balance Sheet | B40: Total current assets | C40: $000 | D40: 30952000 | E40: 16108000 | F40: =D40-E40 -> 14844000 | G40: =IFERROR(D40/E40-1,"n.m.") -> 0.92152967 | H40: Consolidated Balance Sheets.
A41: Balance Sheet | B41: Property, plant & equipment, net | C41: $000 | D41: 42602000 | E41: 21147000 | F41: =D41-E41 -> 21455000 | G41: =IFERROR(D41/E41-1,"n.m.") -> 1.0145647 | H41: Consolidated Balance Sheets.
A42: Balance Sheet | B42: Finance lease right-of-use assets | C42: $000 | D42: 1260000 | E42: 1686000 | F42: =D42-E42 -> -426000 | G42: =IFERROR(D42/E42-1,"n.m.") -> -0.25266904 | H42: Consolidated Balance Sheets.
A43: Balance Sheet | B43: Intangible assets, net | C43: $000 | D43: 1548000 | E43: 2211000 | F43: =D43-E43 -> -663000 | G43: =IFERROR(D43/E43-1,"n.m.") -> -0.29986431 | H43: Consolidated Balance Sheets.
A44: Balance Sheet | B44: Goodwill | C44: $000 | D44: 11809000 | E44: 11129000 | F44: =D44-E44 -> 680000 | G44: =IFERROR(D44/E44-1,"n.m.") -> 0.061101626 | H44: Consolidated Balance Sheets.
A45: Balance Sheet | B45: Deferred tax assets | C45: $000 | D45: 141000 | E45: 696000 | F45: =D45-E45 -> -555000 | G45: =IFERROR(D45/E45-1,"n.m.") -> -0.79741379 | H45: Consolidated Balance Sheets.
A46: Balance Sheet | B46: Other non-current assets | C46: $000 | D46: 2130000 | E46: 2336000 | F46: =D46-E46 -> -206000 | G46: =IFERROR(D46/E46-1,"n.m.") -> -0.088184932 | H46: Consolidated Balance Sheets.
A47: Balance Sheet | B47: Total assets | C47: $000 | D47: 92079000 | E47: 57062000 | F47: =D47-E47 -> 35017000 | G47: =IFERROR(D47/E47-1,"n.m.") -> 0.61366584 | H47: Consolidated Balance Sheets.
... A58: Balance Sheet | B58: Total stockholders' equity | C58: $000 | D58: 2573000 | E58: 4863000 | F58: =D58-E58 -> -2290000 | G58: =IFERROR(D58/E58-1,"n.m.") -> -0.47090273 | H58: Consolidated Balance Sheets.
A59: Balance Sheet | B59: Total liabilities, preferred & equity (check) | C59: $000 | D59: =D56+D57+D58 -> 92079000 | E59: =E56+E57+E58 -> 57062000 | F59: =D59-E59 -> 35017000 | G59: =IFERROR(D59/E59-1,"n.m.") -> 0.61366584 | H59: Consolidated Balance Sheets.
A60: Cash Flow | B60: Net cash provided by operating activities | C60: $000 | D60: 6785000 | E60: 5776000 | F60: 4520000 | G60: =IFERROR(D60/E60-1,"n.m.") -> 0.17468837 | H60: MD&A Cash Flows / Cash Flow Statement.
A61: Cash Flow | B61: Net cash used in investing activities | C61: $000 | D61: -19575000 | E61: -10796000 | F61: -4867000 | G61: =IFERROR(D61/E61-1,"n.m.") -> 0.81317155 | H61: MD&A Cash Flows / Cash Flow Statement.
A62: Cash Flow | B62: Net cash provided by financing activities | C62: $000 | D62: 26350000 | E62: 11830000 | F62: 422000 | G62: =IFERROR(D62/E62-1,"n.m.") -> 1.227388 | H62: MD&A Cash Flows / Cash Flow Statement.
A63: Cash Flow | B63: Effect of exchange rate on cash | C63: $000 | D63: 0 | E63: 0 | F63: 0 | G63: n.m. | H63: Cash Flow Statement.
A64: Cash Flow | B64: Net change in cash | C64: $000 | D64: =D60+D61+D62+D63 -> 13560000 | E64: =E60+E61+E62+E63 -> 6810000 | F64: =F60+F61+F62+F63 -> 75000 | G64: =IFERROR(D64/E64-1,"n.m.") -> 0.99118943 | H64: Cash Flow Statement.
A65: Cash Flow | B65: Cash, beginning of period | C65: $000 | F65: =D65-E65 -> 0 | G65: n.m. | H65: Cash Flow Statement.
A66: Cash Flow | B66: Cash, end of period | C66: $000 | F66: =D66-E66 -> 0 | G66: n.m. | H66: Cash Flow Statement.
A67: Cash Flow Detail | B67: Depreciation and amortization | C67: $000 | D67: 7341000 | E67: 3627000 | F67: 2587000 | G67: =IFERROR(D67/E67-1,"n.m.") -> 1.0239868 | H67: Consolidated Statements of Cash Flows.
A68: Cash Flow Detail | B68: Stock-based compensation | C68: $000 | D68: 1307000 | E68: 981000 | F68: 727000 | G68: =IFERROR(D68/E68-1,"n.m.") -> 0.33231397 | H68: Consolidated Statements of Cash Flows.
A69: Cash Flow Detail | B69: Non-cash lease expense | C69: $000 | F69: =D69-E69 -> 0 | G69: n.m. | H69: Consolidated Statements of Cash Flows.
A70: Cash Flow Detail | B70: Provision for product warranties | C70: $000 | F70: =D70-E70 -> 0 | G70: n.m. | H70: Consolidated Statements of Cash Flows.
A71: Cash Flow Detail | B71: Change in fair value / extinguishment | C71: $000 | F71: =D71-E71 -> 0 | G71: n.m. | H71: Consolidated Statements of Cash Flows.
A72: Cash Flow Detail | B72: Other non-cash items | C72: $000 | F72: =D72-E72 -> 0 | G72: n.m. | H72: Consolidated Statements of Cash Flows.
A73: Cash Flow Detail | B73: (Inc.) / dec. in accounts receivable | C73: $000 | F73: =D73-E73 -> 0 | G73: n.m. | H73: Consolidated Statements of Cash Flows.
A74: Cash Flow Detail | B74: (Inc.) / dec. in inventory | C74: $000 | F74: =D74-E74 -> 0 | G74: n.m. | H74: Consolidated Statements of Cash Flows.
A75: Cash Flow Detail | B75: (Inc.) / dec. in prepaid & other | C75: $000 | F75: =D75-E75 -> 0 | G75: n.m. | H75: Consolidated Statements of Cash Flows.
A76: Cash Flow Detail | B76: Inc. / (dec.) in accounts payable | C76: $000 | F76: =D76-E76 -> 0 | G76: n.m. | H76: Consolidated Statements of Cash Flows.
A77: Cash Flow Detail | B77: Inc. / (dec.) in deferred revenue | C77: $000 | D77: 1153000 | F77: =D77-E77 -> 1153000 | G77: n.m. | H77: Consolidated Statements of Cash Flows.
A78: Cash Flow Detail | B78: Inc. / (dec.) in customer deposits | C78: $000 | F78: =D78-E78 -> 0 | G78: n.m. | H78: Consolidated Statements of Cash Flows.
A79: Cash Flow Detail | B79: Inc. / (dec.) in other liabilities | C79: $000 | F79: =D79-E79 -> 0 | G79: n.m. | H79: Consolidated Statements of Cash Flows.
A80: Cash Flow Detail | B80: Purchases of property, plant & equipment (capex) | C80: $000 | D80: -20737000 | E80: -11163000 | F80: -4415000 | G80: =IFERROR(D80/E80-1,"n.m.") -> 0.85765475 | H80: Consolidated Statements of Cash Flows.
A81: Cash Flow Detail | B81: Purchases of marketable securities | C81: $000 | F81: =D81-E81 -> 0 | G81: n.m. | H81: Consolidated Statements of Cash Flows.
A82: Cash Flow Detail | B82: Maturities and sales of marketable securities | C82: $000 | F82: =D82-E82 -> 0 | G82: n.m. | H82: Consolidated Statements of Cash Flows.
A83: Cash Flow Detail | B83: Proceeds from debt issuance / SpaceX Bridge Loan | C83: $000 | D83: 16055000 | F83: =D83-E83 -> 16055000 | G83: n.m. | H83: Consolidated Statements of Cash Flows.
A84: Cash Flow Detail | B84: Repayments of debt | C84: $000 | D84: -6781000 | F84: =D84-E84 -> -6781000 | G84: n.m. | H84: Consolidated Statements of Cash Flows.
A85: Cash Flow Detail | B85: Proceeds from exercise of stock options | C85: $000 | F85: =D85-E85 -> 0 | G85: n.m. | H85: Consolidated Statements of Cash Flows.
A86: Cash Flow Detail | B86: Proceeds from sale of capital stock | C86: $000 | D86: 5706000 | F86: =D86-E86 -> 5706000 | G86: n.m. | H86: Consolidated Statements of Cash Flows.
A87: Cash Flow Detail | B87: Repurchases of common stock (xAI merger) | C87: $000 | F87: =D87-E87 -> 0 | G87: n.m. | H87: Consolidated Statements of Cash Flows.
A88: Cash Flow Detail | B88: Repurchase of common stock | C88: $000 | F88: =D88-E88 -> 0 | G88: n.m. | H88: Consolidated Statements of Cash Flows.
A89: Cash Flow Detail | B89: Tax withheld related to RSU settlement | C89: $000 | F89: =D89-E89 -> 0 | G89: n.m. | H89: Consolidated Statements of Cash Flows.
A90: Cash Flow Detail | B90: Payments of deferred offering costs | C90: $000 | F90: =D90-E90 -> 0 | G90: n.m. | H90: Consolidated Statements of Cash Flows.

Sheet KPIs
A1: SpaceX KPI Summary — Annual (FY 2025 / FY 2024 / FY 2023)
A3: Metric | B3: Units | C3: FY 2025 | D3: FY 2024 | E3: FY 2023 | F3: Notes / Formula | G3: Source
A4: Total revenue growth | B4: % | C4: =Annual_Financials!D6/Annual_Financials!E6-1 -> 0.33242954 | D4: =Annual_Financials!E6/Annual_Financials!F6-1 -> 0.34928276 | E4: n.a. | F4: FY25 / FY24 - 1 | G4: SpaceX S-1, §3
A5: Space segment revenue | B5: 0 | C5: 4086000 | D5: 3796000 | E5: 3557000 | F5: Customer launches + Launch & Development | G5: SpaceX S-1, §5
A6: Connectivity segment revenue | B6: 0 | C6: 11387000 | D6: 7599000 | E6: 3869000 | F6: Consumer Starlink + Enterprise/Gov + Mobile | G6: SpaceX S-1, §5
A7: AI segment revenue | B7: 0 | C7: 3201000 | D7: 2620000 | E7: 2961000 | F7: Advertising + AI Solutions & Infrastructure | G7: SpaceX S-1, §5
A8: Gross margin | B8: % | C8: =Annual_Financials!D10/Annual_Financials!D6 -> 0.49389526 | D8: =Annual_Financials!E10/Annual_Financials!E6 -> 0.42946843 | E8: =Annual_Financials!F10/Annual_Financials!F6 -> 0.41176471 | F8: Gross profit / revenue | G8: Annual_Financials
A9: Operating margin | B9: % | C9: =Annual_Financials!D15/Annual_Financials!D6 -> -0.13864196 | D9: =Annual_Financials!E15/Annual_Financials!E6 -> 0.033250089 | E9: =Annual_Financials!F15/Annual_Financials!F6 -> -0.33744103 | F9: Operating income (loss) / revenue | G9: Annual_Financials
A10: Net margin | B10: % | C10: =Annual_Financials!D21/Annual_Financials!D6 -> -0.26437828 | D10: =Annual_Financials!E21/Annual_Financials!E6 -> 0.056439529 | E10: =Annual_Financials!F21/Annual_Financials!F6 -> -0.44555695 | F10: Net income (loss) / revenue | G10: Annual_Financials
A11: Adjusted EBITDA | B11: 0 | C11: 6584000 | D11: 5350000 | E11: 3821000 | F11: Non-GAAP EBITDA | G11: SpaceX S-1, §2-3
A12: Adjusted EBITDA margin | B12: % | C12: =C11/Annual_Financials!D6 -> 0.35257577 | D12: =D11/Annual_Financials!E6 -> 0.38173386 | E12: =E11/Annual_Financials!F6 -> 0.36786368 | F12: Adj EBITDA / revenue | G12: Annual_Financials
A13: R&D as % of revenue | B13: % | C13: =Annual_Financials!D11/Annual_Financials!D6 -> 0.46283603 | D13: =Annual_Financials!E11/Annual_Financials!E6 -> 0.24716375 | E13: =Annual_Financials!F11/Annual_Financials!F6 -> 0.20265717 | F13: R&D / revenue | G13: Annual_Financials
A14: SG&A as % of revenue | B14: % | C14: =Annual_Financials!D12/Annual_Financials!D6 -> 0.14158723 | D14: =Annual_Financials!E12/Annual_Financials!E6 -> 0.1293614 | E14: =Annual_Financials!F12/Annual_Financials!F6 -> 0.16029652 | F14: SG&A / revenue | G14: Annual_Financials
A15: Starlink subscribers (millions) | B15: M | C15: 8.9 | D15: 4.4 | E15: 2.3 | F15: Period-end Starlink subscriber count | G15: SpaceX S-1, §7
A16: Starlink monthly ARPU | B16: $ | C16: 81 | D16: 91 | E16: 99 | F16: Consumer monthly ARPU | G16: SpaceX S-1, §7
A17: Starlink satellites in LEO | B17: # | C17: 9600 | E17: Broadband + mobile satellites in low earth orbit | F17: Broadband + mobile satellites in LEO | G17: SpaceX S-1, §7
A18: Countries / markets served | B18: # | C18: 164 | E18: Countries, territories, and markets | F18: Countries, territories, and markets | G18: SpaceX S-1, §7
A19: Mass to orbit (metric tons) | B19: MT | C19: 2213 | D19: 1699 | E19: 1210 | F19: Total mass delivered to orbit | G19: SpaceX S-1, §6
A20: Total launches | B20: # | C20: 170 | D20: 138 | E20: 98 | F20: Falcon + Starship launches | G20: SpaceX S-1, §6
A21: Customer Falcon launches | B21: # | C21: 43 | D21: 45 | E21: 33 | F21: External customer launches | G21: SpaceX S-1, §6
A22: Internal Falcon launches | B22: # | C22: 122 | D22: 89 | E22: 63 | F22: Starlink internal launches | G22: SpaceX S-1, §6
A23: AI compute capacity (GW) | B23: GW | C23: 0.8 | D23: 0.3 | E23: 0 | F23: Nameplate compute draw | G23: SpaceX S-1, §8
A24: Grok/X monthly active users (M) | B24: M | C24: 520 | D24: 520 | E24: Combined Grok + X MAUs | F24: Combined Grok + X MAUs | G24: SpaceX S-1, §8
A25: AI paid subscribers (M) | B25: M | C25: 6.3 | E25: X Premium + SuperGrok subscribers | F25: X Premium + SuperGrok subscribers | G25: SpaceX S-1, §8
A26: Total capex | B26: 0 | C26: 20737000 | D26: 11163000 | E26: 4415000 | F26: Across Space, Connectivity, AI | G26: SpaceX S-1, §9
A27: Space capex | B27: 0 | C27: 3832000 | D27: 2032000 | E27: 1497000 | F27: Falcon, Starship, launch facilities | G27: SpaceX S-1, §9
A28: Connectivity capex | B28: 0 | C28: 4178000 | D28: 3498000 | E28: 2455000 | F28: Starlink satellites + ground stations | G28: SpaceX S-1, §9
A29: AI capex | B29: 0 | C29: 12727000 | D29: 5633000 | E29: 463000 | F29: GPUs, data centers, power | G29: SpaceX S-1, §9
A30: Operating cash flow | B30: 0 | C30: =Annual_Financials!D60 -> 6785000 | D30: =Annual_Financials!E60 -> 5776000 | E30: =Annual_Financials!F60 -> 4520000 | F30: Net cash from operating activities | G30: Annual_Financials
A31: Free cash flow (OCF - Capex) | B31: 0 | C31: =Annual_Financials!D60+Annual_Financials!D80 -> -13952000 | D31: =Annual_Financials!E60+Annual_Financials!E80 -> -5387000 | E31: =Annual_Financials!F60+Annual_Financials!F80 -> 105000 | F31: OCF minus capex | G31: Derived (OCF - capex)
A32: Cash + Marketable securities | B32: 0 | C32: =Annual_Financials!D34+Annual_Financials!D35 -> 24747000 | D32: =Annual_Financials!E34+Annual_Financials!E35 -> 12185000 | E32: Liquid assets | F32: Liquid assets (cash + mkt sec) | G32: Annual_Financials
A33: Total debt (current + LT) | B33: 0 | C33: =Annual_Financials!D50+Annual_Financials!D54 -> 22896000 | D33: =Annual_Financials!E50+Annual_Financials!E54 -> 13793000 | E33: Including finance leases | F33: Including finance leases | G33: Annual_Financials
A34: Net debt | B34: 0 | C34: =C33-C32 -> -1851000 | D34: =D33-D32 -> 1608000 | E34: Total debt - liquidity | F34: Total debt - liquidity | G34: Derived
A35: Deferred revenue (total) | B35: 0 | C35: =Annual_Financials!D49+Annual_Financials!D53 -> 12116000 | D35: =Annual_Financials!E49+Annual_Financials!E53 -> 10179000 | E35: Current + non-current | F35: Current + non-current deferred revenue | G35: Annual_Financials
A36: Backlog | B36: 0 | C36: 28377000 | D36: 28377000 | E36: Contracted future revenue | F36: Contracted future revenue | G36: SpaceX S-1, §12
A37: Bridge Loan outstanding | B37: 0 | C37: 20000000 | E37: Bridge Loan principal | F37: Bridge Loan principal | G37: SpaceX S-1, §13
C38: =Annual_Financials!D40/Annual_Financials!E40-1 -> 0.92152967
C39: =Annual_Financials!D41/Annual_Financials!E41-1 -> 1.0145647
C40: =Annual_Financials!D42/Annual_Financials!E42-1 -> -0.25266904
C41: =Annual_Financials!D43/Annual_Financials!E43-1 -> -0.29986431
C42: =Annual_Financials!D44/Annual_Financials!E44-1 -> 0.061101626
C43: =Annual_Financials!D45/Annual_Financials!E45-1 -> -0.79741379
C44: =Annual_Financials!D46/Annual_Financials!E46-1 -> -0.088184932
C45: =Annual_Financials!D47/Annual_Financials!E47-1 -> 0.61366584

Sheet Checks
A1: Validation Checks — SpaceX Model
A3: Check | B3: Formula / Basis | C3: Result | D3: Expected / Interpretation | E3: Status
A4: Revenue tie (FY 2025) | B4: Products + Services revenue = Total revenue (D6) | C4: =Annual_Financials!D4+Annual_Financials!D5-Annual_Financials!D6 -> 0 | D4: 0 | E4: =IF(C4=0,"OK","CHECK") -> OK
A5: Revenue tie (FY 2024) | B5: Products + Services revenue = Total revenue (E6) | C5: =Annual_Financials!E4+Annual_Financials!E5-Annual_Financials!E6 -> 0 | D5: 0 | E5: =IF(C5=0,"OK","CHECK") -> OK
A6: Cost of revenue tie (FY 2025) | B6: Products + Services COGS = Total COGS (D9). NOTE: SpaceX doesn't disclose by line; D7/D8 left blank. | C6: =IF(AND(Annual_Financials!D7="",Annual_Financials!D8=""),0,Annual_Financials!D7+Annual_Financials!D8-Annual_Financials!D9) -> 0 | D6: 0 | E6: =IF(C6=0,"OK","CHECK") -> OK
A7: Cost of revenue tie (FY 2024) | B7: Products + Services COGS = Total COGS (E9). NOTE: SpaceX doesn't disclose by line; E7/E8 left blank. | C7: =IF(AND(Annual_Financials!E7="",Annual_Financials!E8=""),0,Annual_Financials!E7+Annual_Financials!E8-Annual_Financials!E9) -> 0 | D7: 0 | E7: =IF(C7=0,"OK","CHECK") -> OK
A8: Gross profit tie (FY 2025) | B8: Total revenue - Total COGS = Gross profit (D10) | C8: =Annual_Financials!D6-Annual_Financials!D9-Annual_Financials!D10 -> 0 | D8: 0 | E8: =IF(C8=0,"OK","CHECK") -> OK
A9: Gross profit tie (FY 2024) | B9: Total revenue - Total COGS = Gross profit (E10) | C9: =Annual_Financials!E6-Annual_Financials!E9-Annual_Financials!E10 -> 0 | D9: 0 | E9: =IF(C9=0,"OK","CHECK") -> OK
A10: OpEx tie (FY 2025) | B10: R&D + SG&A + Restructuring + Impairment vs sum-of-parts check | C10: =Annual_Financials!D11+Annual_Financials!D12+Annual_Financials!D13+Annual_Financials!D14-(Annual_Financials!D10-Annual_Financials!D15) -> 0 | D10: 0 | E10: =IF(C10=0,"OK","CHECK") -> OK
A11: OpEx tie (FY 2024) | B11: R&D + SG&A + Restructuring + Impairment vs sum-of-parts check | C11: =Annual_Financials!E11+Annual_Financials!E12+Annual_Financials!E13+Annual_Financials!E14-(Annual_Financials!E10-Annual_Financials!E15) -> 0 | D11: 0 | E11: =IF(C11=0,"OK","CHECK") -> OK
A12: Operating income tie (FY 2025) | B12: Gross profit - (R&D + SG&A + Restr + Impair) - Operating loss (D15) = 0 | C12: =Annual_Financials!D10-(Annual_Financials!D11+Annual_Financials!D12+Annual_Financials!D13+Annual_Financials!D14)-Annual_Financials!D15 -> 0 | D12: 0 | E12: =IF(C12=0,"OK","CHECK") -> OK
A13: Operating income tie (FY 2024) | B13: Gross profit - (R&D + SG&A + Restr + Impair) - Operating income/loss (E15) = 0 | C13: =Annual_Financials!E10-(Annual_Financials!E11+Annual_Financials!E12+Annual_Financials!E13+Annual_Financials!E14)-Annual_Financials!E15 -> 0 | D13: 0 | E13: =IF(C13=0,"OK","CHECK") -> OK
A14: Net income tie (FY 2025) | B14: Pretax (D19) - Tax (D20) - Net loss (D21) = 0 | C14: =Annual_Financials!D19-Annual_Financials!D20-Annual_Financials!D21 -> 0 | D14: 0 | E14: =IF(C14=0,"OK","CHECK") -> OK
A15: Net income tie (FY 2024) | B15: Pretax (E19) - Tax (E20) - Net income (E21) = 0 | C15: =Annual_Financials!E19-Annual_Financials!E20-Annual_Financials!E21 -> 0 | D15: 0 | E15: =IF(C15=0,"OK","CHECK") -> OK
A16: Basic shares subtotal exists | B16: Share_Count!C24 (basic post-IPO incl. greenshoe) | C16: =Share_Count!C24 -> 12520310769 | D16: > 0 once cap table is populated | E16: =IF(C16>0,"OK","CHECK") -> OK
A17: Fully diluted subtotal exists | B17: Share_Count!C26 (fully diluted) | C17: =Share_Count!C26 -> 15739210769 | D17: > 0 once cap table is populated | E17: =IF(C17>0,"OK","CHECK") -> OK
A18: Required unknown fields | B18: Count of cap-table rows flagged as required but not yet populated | C18: =Share_Count!C27 -> 2 | D18: 0 once final S-1 is populated | E18: =IF(C18>0,"OK - prelim blanks","CHECK") -> OK - prelim blanks
A19: Balance sheet tie (Dec 31 2025) | B19: Total assets (D47) = Total liab + Pref + Equity (D59) | C19: =Annual_Financials!D47-Annual_Financials!D59 -> 0 | D19: 0 | E19: =IF(ABS(C19)<1,"OK","CHECK") -> OK
A20: Balance sheet tie (Dec 31 2024) | B20: Total assets (E47) = Total liab + Pref + Equity (E59) | C20: =Annual_Financials!E47-Annual_Financials!E59 -> 0 | D20: 0 | E20: =IF(ABS(C20)<1,"OK","CHECK") -> OK
A21: FY 2025 revenue ties to disclosed | B21: Annual_Financials!D6 = $18,674M ($000) | C21: =Annual_Financials!D6-18674000 -> 0 | D21: 0 | E21: =IF(C21=0,"OK","CHECK") -> OK
A22: FY 2025 net loss ties to disclosed | B22: Annual_Financials!D21 = -$4,937M | C22: =Annual_Financials!D21-(-4937000) -> 0 | D22: 0 | E22: =IF(C22=0,"OK","CHECK") -> OK
A23: FY 2025 Adj EBITDA ties to disclosed | B23: Annual_Financials!D27 = $6,584M | C23: =Annual_Financials!D27-6584000 -> 0 | D23: 0 | E23: =IF(C23=0,"OK","CHECK") -> OK
A24: Pro forma share count ties to disclosed | B24: Share_Count!C24 = 12,520,310,769 | C24: =Share_Count!C24-12520310769 -> 0 | D24: 0 | E24: =IF(C24=0,"OK","CHECK") -> OK
A25: FD shares tie to aggressive walk | B25: Share_Count!C26 = 15,739,210,769 (per markdown §16) | C25: =Share_Count!C26-15739210769 -> 0 | D25: 0 | E25: =IF(C25=0,"OK","CHECK") -> OK
A26: IPO_Analysis FD shares (post-IPO + greenshoe + awards) | B26: IPO_Analysis!C32 should be ~14.02B (pro forma + IPO + options + RSUs + perf + EchoStar) | C26: =IPO_Analysis!C32 -> 14765110769 | D26: ~14,017,610,769 | E26: =IF(IPO_Analysis!C32>13000000000,"OK","CHECK") -> OK
A27: IPO midpoint price within range | B27: C13 should be midpoint of C12 (low) and C14 (high) | C27: =IPO_Analysis!C13-(IPO_Analysis!C12+IPO_Analysis!C14)/2 -> 0 | D27: 0 | E27: =IF(ABS(C27)<0.01,"OK","CHECK") -> OK
A28: FD market cap in target range $1.75T - $1.90T | B28: IPO_Analysis!F35 at midpoint | C28: =IPO_Analysis!F35/1000000000 -> 1845.6388 | D28: $1.75T - $1.90T (post-$100B raise) | E28: =IF(AND(IPO_Analysis!F35>1750000000000,IPO_Analysis!F35<1900000000000),"OK","CHECK") -> OK
A29: FY 2025 op margin negative (loss year) | B29: KPIs!C9 should be < 0 | C29: =KPIs!C9 -> -0.13864196 | D29: < 0 | E29: =IF(KPIs!C9<0,"OK","CHECK") -> OK
A30: FY 2025 revenue growth >25% | B30: KPIs!C4 should be ~33% | C30: =KPIs!C4 -> 0.33242954 | D30: ~33% | E30: =IF(KPIs!C4>0.25,"OK","CHECK") -> OK
A31: Segment Adj EBITDA sums to consolidated (FY 2025) | B31: IPO_Analysis!D88 (sum of segments) = Annual_Financials!D27 (consolidated) | C31: =IPO_Analysis!D88-Annual_Financials!D27 -> 0 | D31: 0 | E31: =IF(C31=0,"OK","CHECK") -> OK
A32: Segment Adj EBITDA sums to consolidated (FY 2024) | B32: IPO_Analysis!C88 (sum of segments) = Annual_Financials!E27 (consolidated) | C32: =IPO_Analysis!C88-Annual_Financials!E27 -> 0 | D32: 0 | E32: =IF(C32=0,"OK","CHECK") -> OK
